README.md
setup.cfg
setup.py
func_pyspark/__init__.py
func_pyspark/func_pyspark.py
func_pyspark.egg-info/PKG-INFO
func_pyspark.egg-info/SOURCES.txt
func_pyspark.egg-info/dependency_links.txt
func_pyspark.egg-info/not-zip-safe
func_pyspark.egg-info/top_level.txt