Metadata-Version: 2.1
Name: func-pyspark
Version: 0.0.4
Summary: multiple function for  pyspark dataframe
Home-page: UNKNOWN
Author-email: ranjitmaity95@gmail.com
License: UNKNOWN
Platform: UNKNOWN
